ElasticsearchMock-1.1.2.dist-info/METADATA
ElasticsearchMock-1.1.2.dist-info/RECORD
ElasticsearchMock-1.1.2.dist-info/WHEEL
ElasticsearchMock-1.1.2.dist-info/top_level.txt
elasticmock/__init__.py
elasticmock/fake_elasticsearch.py
elasticmock/utilities/__init__.py
