Metadata-Version: 2.1
Name: ElasticsearchMock
Version: 1.1.2
Summary: Python Elasticsearch Mock for test purposes
Home-page: https://github.com/jmlw/elasticmock
Author: Josh Wood
Author-email: josh.m.l.wood@gmail.com
License: MIT
Platform: any
Classifier: Environment :: Web Environment
Classifier: Intended Audience :: Developers
Classifier: Operating System :: OS Independent
Classifier: Programming Language :: Python
Classifier: Topic :: Software Development :: Libraries :: Python Modules
Requires-Dist: elasticsearch (<6.0.0,>=5.0.0)
Requires-Dist: mock (<=1.0.1)
